streamiopipe/__init__.py
streamiopipe-0.1.1.dist-info/METADATA
streamiopipe-0.1.1.dist-info/WHEEL
streamiopipe-0.1.1.dist-info/RECORD
